{"success": true, "converted_code": "```csharp\n/// <summary>\n/// Processes a CircularA object by doubling its ValueA property.\n/// In C#, classes are reference types, so passing an instance of CircularA\n/// is equivalent to passing a pointer in C. The method can modify the object's state.\n/// The null check `if (a)` is translated to `if (a != null)`.\n/// </summary>\n/// <param name=\"a\">The CircularA object to process. Can be null.</param>\npublic static void ProcessA(CircularA a)\n{\n    if (a != null)\n    {\n        a.ValueA *= 2;\n    }\n}\n\n// Note: The C 'CircularA' struct is assumed to be converted to a C# class\n// because the C function takes a pointer and can handle null, which maps\n// directly to a nullable reference type (a class) in C#.\n//\n// public class CircularA\n// {\n//     public int ValueA;\n//     // ... other members\n// }\n```", "explanation": "Successfully converted with Gemini", "warnings": [], "tokens_used": 2169, "processing_time": 19.984598875045776}